jupyter_mcp/__init__.py
jupyter_mcp/__version__.py
jupyter_mcp/server.py
jupyter_mcp/daemon/__init__.py
jupyter_mcp/daemon/client.py
jupyter_mcp/daemon/kernel_daemon.py
jupyter_mcp/environment/__init__.py
jupyter_mcp/environment/detector.py
jupyter_mcp/environment/uv_manager.py
jupyter_mcp/handlers/__init__.py
jupyter_mcp/handlers/error_handler.py
jupyter_mcp/handlers/response.py
jupyter_mcp/notebook/__init__.py
jupyter_mcp/tools/__init__.py
jupyter_mcp/tools/debugging.py
jupyter_mcp/tools/environment.py
jupyter_mcp/tools/execution.py
jupyter_mcp/tools/guidance.py
jupyter_mcp/tools/notebook.py
jupyter_mcp/utils/__init__.py
jupyter_mcp/utils/constants.py
ml_jupyter_mcp-2.0.0.dist-info/METADATA
ml_jupyter_mcp-2.0.0.dist-info/WHEEL
ml_jupyter_mcp-2.0.0.dist-info/entry_points.txt
ml_jupyter_mcp-2.0.0.dist-info/top_level.txt
ml_jupyter_mcp-2.0.0.dist-info/RECORD
